vineyard/drivers/io/__init__.py
vineyard/drivers/io/fsspec_adaptors.py
vineyard/drivers/io/kube_ssh.sh
vineyard/drivers/io/ossfs.py
vineyard/drivers/io/ssh.sh
vineyard/drivers/io/stream.py
vineyard/drivers/io/adaptors/__init__.py
vineyard/drivers/io/adaptors/deserializer.py
vineyard/drivers/io/adaptors/dump_dataframe.py
vineyard/drivers/io/adaptors/parse_bytes_to_dataframe.py
vineyard/drivers/io/adaptors/parse_dataframe_to_bytes.py
vineyard/drivers/io/adaptors/read_bytes.py
vineyard/drivers/io/adaptors/read_bytes_collection.py
vineyard/drivers/io/adaptors/read_orc.py
vineyard/drivers/io/adaptors/read_parquet.py
vineyard/drivers/io/adaptors/read_vineyard_dataframe.py
vineyard/drivers/io/adaptors/serializer.py
vineyard/drivers/io/adaptors/write_bytes.py
vineyard/drivers/io/adaptors/write_bytes_collection.py
vineyard/drivers/io/adaptors/write_orc.py
vineyard/drivers/io/adaptors/write_parquet.py
vineyard/drivers/io/adaptors/write_vineyard_dataframe.py
vineyard/drivers/io/tests/__init__.py
vineyard/drivers/io/tests/test_migrate_stream.py
vineyard/drivers/io/tests/test_open.py
vineyard/drivers/io/tests/test_ossfs.py
vineyard/drivers/io/tests/test_serialize.py
vineyard_io-0.24.2.dist-info/LICENSE
vineyard_io-0.24.2.dist-info/METADATA
vineyard_io-0.24.2.dist-info/NOTICE.txt
vineyard_io-0.24.2.dist-info/WHEEL
vineyard_io-0.24.2.dist-info/entry_points.txt
vineyard_io-0.24.2.dist-info/top_level.txt
vineyard_io-0.24.2.dist-info/RECORD
